<?xml version="1.0" encoding="UTF-8"?>
<openerp>
    <data noupdate="True">
        <record model='ir.cron' id='update_costs'>
            <field name='name'>Update product costs</field>
            <field name='active'>True</field>
            <field name='priority'>5</field>
            <field name='interval_number'>1</field>
            <field name='number_call'>-1</field>
            <field name='interval_type'>days</field>
            <field name='model'>product.product</field>
            <field name='function'>_update_cost</field>
            <field name='args'>()</field>
        </record>
    </data>
</openerp>

